README
setup.py
bin/django-startproject.py
django_startproject/__init__.py
django_startproject/management.py
django_startproject/utils.py
django_startproject.egg-info/PKG-INFO
django_startproject.egg-info/SOURCES.txt
django_startproject.egg-info/dependency_links.txt
django_startproject.egg-info/top_level.txt