Metadata-Version: 1.0
Name: django-startproject
Version: 1.0a
Summary: Create a Django project layout based on Lincoln Loop best practices.
Home-page: UNKNOWN
Author: Lincoln Loop
Author-email: info@lincolnloop.com
License: UNKNOWN
Platform: UNKNOWN
Classifier: Development Status :: 3 - Alpha
Classifier: Environment :: Web Environment
Classifier: Framework :: Django
Classifier: Intended Audience :: Developers
Classifier: License :: OSI Approved :: MIT License
Classifier: Operating System :: OS Independent
Classifier: Programming Language :: Python
Classifier: Topic :: Software Development :: Libraries :: Python Modules
